snippets_api/snippets.py
snippets_api/videos.py
snippets_api-0.5.0.dist-info/METADATA
snippets_api-0.5.0.dist-info/WHEEL
snippets_api-0.5.0.dist-info/RECORD
