Metadata-Version: 2.1
Name: snippets-api
Version: 0.5.0
Summary: 
Author: Jett
Author-email: jettcrowson@gmail.com
Requires-Python: >=3.12,<4.0
Classifier: Programming Language :: Python :: 3
Classifier: Programming Language :: Python :: 3.12
Requires-Dist: pydantic (>=2.9.1,<3.0.0)
